grader/__init__.py
grader/api/__init__.py
grader/api/courses_api.py
grader/api/students_api.py
grader/api/tasks_api.py
grader/checking/__init__.py
grader/checking/base.py
grader/checking/ch_checker.py
grader/checking/checking.py
grader/checking/hdfs_checker.py
grader/checking/k8s_checker.py
grader/checking/spark_checker.py
grader/checking/utils.py
grader/cli.py
grader/client/__init__.py
grader/client/grader.py
grader/db/__init__.py
grader/db/init_db.py
grader/db/tasks.py
grader/env.py
grader/faststream_tasks/__init__.py
grader/faststream_tasks/schemes.py
grader/faststream_tasks/tasks.py
grader/schemes.py
grader/services/__init__.py
grader/services/checker.py
grader/ui/main.py
grader/ui/pages/submissions.py
k8s_grader-0.1.2.dist-info/LICENSE
k8s_grader-0.1.2.dist-info/METADATA
k8s_grader-0.1.2.dist-info/WHEEL
k8s_grader-0.1.2.dist-info/entry_points.txt
k8s_grader-0.1.2.dist-info/RECORD
