Metadata-Version: 2.1
Name: k8s-grader
Version: 0.1.2
Summary: 
Author: fonhorst
Author-email: fonhorst@alipoov.nb@gmail.com
Requires-Python: >=3.10,<3.13
Classifier: Programming Language :: Python :: 3
Classifier: Programming Language :: Python :: 3.10
Classifier: Programming Language :: Python :: 3.11
Classifier: Programming Language :: Python :: 3.12
Provides-Extra: pyspark
Provides-Extra: ui
Requires-Dist: aio-pika (>=9.5.5,<10.0.0)
Requires-Dist: aiocache (>=0.12.1,<0.13.0)
Requires-Dist: aiohttp
Requires-Dist: arango (>=0.2.1,<0.3.0)
Requires-Dist: asyncpg (>=0.30.0,<0.31.0)
Requires-Dist: celery (>=5.2.7,<6.0.0)
Requires-Dist: clickhouse-driver (>=0.2.0,<0.3.0)
Requires-Dist: dill
Requires-Dist: docker (>=6.0.1,<7.0.0)
Requires-Dist: elasticsearch (>=7.17.0,<8.0.0)
Requires-Dist: fastapi (>=0.100.0,<0.101.0)
Requires-Dist: fastapi-pagination (>=0.11.4,<0.12.0)
Requires-Dist: faststream (>=0.5.23,<0.6.0)
Requires-Dist: filelock (>=3.13.0,<4.0.0)
Requires-Dist: hdfs (>=2.7.3,<3.0.0)
Requires-Dist: httpx (>=0.25.0,<0.26.0)
Requires-Dist: kafka (>=1.3.5,<2.0.0)
Requires-Dist: kafka-python (>=2.0.2,<3.0.0)
Requires-Dist: kubernetes (>=18.20.0,<19.0.0)
Requires-Dist: nest-asyncio (>=1.6.0,<2.0.0) ; extra == "ui"
Requires-Dist: pandas (>=2.2.3,<3.0.0)
Requires-Dist: psutil (>=5.9.8,<6.0.0)
Requires-Dist: psycopg2-binary (>=2.9.6,<3.0.0)
Requires-Dist: pyarrow (>=19.0.1,<20.0.0)
Requires-Dist: pydantic (>=2.11.1,<3.0.0)
Requires-Dist: pyspark (>=3.5.5,<4.0.0) ; extra == "pyspark"
Requires-Dist: python-arango (>=7.5.0,<8.0.0)
Requires-Dist: python-jose (>=3.3.0,<4.0.0)
Requires-Dist: python-redis-cache (>=1.2.0,<2.0.0)
Requires-Dist: pyyaml (>=6.0.1,<7.0.0)
Requires-Dist: redis (>=4.5.3,<5.0.0)
Requires-Dist: requests (<2.32.0)
Requires-Dist: requests-toolbelt (>=1.0.0,<2.0.0)
Requires-Dist: sqlalchemy (>=2.0.7,<3.0.0)
Requires-Dist: streamlit (>=1.44.1,<2.0.0) ; extra == "ui"
Requires-Dist: typer (>=0.15.2,<0.16.0)
Requires-Dist: uvicorn (>=0.21.1,<0.22.0)
